[
  {
    "id": 45,
    "patternId": 110,
    "sentenceId": 431,
    "exactText": "I was ",
    "patternText": "I was *",
    "en": "Right, so back in 2005, when I was 27, my two best friends got engaged.",
    "videoTitle": "《老爸老妈浪漫史》第一季第2集——保姆级看美剧学英语~提升口语听力 p04 第二集01无字幕",
    "videoId": "v-e90b4914-hr86"
  },
  {
    "id": 46,
    "patternId": 150,
    "sentenceId": 432,
    "exactText": "get married",
    "patternText": "get married",
    "en": "And it got me thinking, maybe I should get married.",
    "videoTitle": "《老爸老妈浪漫史》第一季第2集——保姆级看美剧学英语~提升口语听力 p04 第二集01无字幕",
    "videoId": "v-e90b4914-hr86"
  },
  {
    "id": 47,
    "patternId": 135,
    "sentenceId": 438,
    "exactText": "going to ",
    "patternText": "going to *",
    "en": "Have you met Ted? No, no, no, no, we're not going to have you met Ted. Hi, have you met Ted?",
    "videoTitle": "《老爸老妈浪漫史》第一季第2集——保姆级看美剧学英语~提升口语听力 p04 第二集01无字幕",
    "videoId": "v-e90b4914-hr86"
  },
  {
    "id": 48,
    "patternId": 110,
    "sentenceId": 440,
    "exactText": "I was ",
    "patternText": "I was *",
    "en": "But after just one date, I was in love with her.",
    "videoTitle": "《老爸老妈浪漫史》第一季第2集——保姆级看美剧学英语~提升口语听力 p04 第二集01无字幕",
    "videoId": "v-e90b4914-hr86"
  },
  {
    "id": 49,
    "patternId": 104,
    "sentenceId": 447,
    "exactText": "I mean",
    "patternText": "I mean *",
    "en": "I mean, I made a complete fool of myself.",
    "videoTitle": "《老爸老妈浪漫史》第一季第2集——保姆级看美剧学英语~提升口语听力 p04 第二集01无字幕",
    "videoId": "v-e90b4914-hr86"
  },
  {
    "id": 50,
    "patternId": 110,
    "sentenceId": 451,
    "exactText": "I was",
    "patternText": "I was *",
    "en": "I wasn't in love with her, okay?",
    "videoTitle": "《老爸老妈浪漫史》第一季第2集——保姆级看美剧学英语~提升口语听力 p04 第二集01无字幕",
    "videoId": "v-e90b4914-hr86"
  },
  {
    "id": 51,
    "patternId": 110,
    "sentenceId": 452,
    "exactText": "I was ",
    "patternText": "I was *",
    "en": "I was briefly in love with the abstract concept of getting married.",
    "videoTitle": "《老爸老妈浪漫史》第一季第2集——保姆级看美剧学英语~提升口语听力 p04 第二集01无字幕",
    "videoId": "v-e90b4914-hr86"
  },
  {
    "id": 52,
    "patternId": 104,
    "sentenceId": 488,
    "exactText": "I mean",
    "patternText": "I mean *",
    "en": "I mean, he's sweet, he's charming, he's just looking for something a little bit more serious than I am.",
    "videoTitle": "《老爸老妈浪漫史》第一季第2集——保姆级看美剧学英语~提升口语听力 p04 第二集01无字幕",
    "videoId": "v-e90b4914-hr86"
  },
  {
    "id": 53,
    "patternId": 104,
    "sentenceId": 489,
    "exactText": "I mean",
    "patternText": "I mean *",
    "en": "I mean, the most I can handle right now is something casual.",
    "videoTitle": "《老爸老妈浪漫史》第一季第2集——保姆级看美剧学英语~提升口语听力 p04 第二集01无字幕",
    "videoId": "v-e90b4914-hr86"
  },
  {
    "id": 54,
    "patternId": 140,
    "sentenceId": 491,
    "exactText": "Are you kidding",
    "patternText": "are you kidding",
    "en": "Are you kidding?",
    "videoTitle": "《老爸老妈浪漫史》第一季第2集——保姆级看美剧学英语~提升口语听力 p04 第二集01无字幕",
    "videoId": "v-e90b4914-hr86"
  },
  {
    "id": 55,
    "patternId": 105,
    "sentenceId": 496,
    "exactText": "you know ",
    "patternText": "You know *",
    "en": "I'm gonna be a mushroom cloud of casual, you know why?",
    "videoTitle": "《老爸老妈浪漫史》第一季第2集——保姆级看美剧学英语~提升口语听力 p04 第二集01无字幕",
    "videoId": "v-e90b4914-hr86"
  }
]